accelbyte_py_sdk/api/legal/__init__.py
accelbyte_py_sdk/api/legal/errors.py
accelbyte_py_sdk/api/legal/models/__init__.py
accelbyte_py_sdk/api/legal/models/accept_agreement_request.py
accelbyte_py_sdk/api/legal/models/accept_agreement_response.py
accelbyte_py_sdk/api/legal/models/create_base_policy_request.py
accelbyte_py_sdk/api/legal/models/create_base_policy_request_v2.py
accelbyte_py_sdk/api/legal/models/create_base_policy_response.py
accelbyte_py_sdk/api/legal/models/create_localized_policy_version_request.py
accelbyte_py_sdk/api/legal/models/create_localized_policy_version_response.py
accelbyte_py_sdk/api/legal/models/create_policy_request.py
accelbyte_py_sdk/api/legal/models/create_policy_response.py
accelbyte_py_sdk/api/legal/models/create_policy_version_request.py
accelbyte_py_sdk/api/legal/models/create_policy_version_response.py
accelbyte_py_sdk/api/legal/models/download_exported_agreements_in_csv_response.py
accelbyte_py_sdk/api/legal/models/error_entity.py
accelbyte_py_sdk/api/legal/models/field_validation_error.py
accelbyte_py_sdk/api/legal/models/initiate_export_agreements_to_csv_response.py
accelbyte_py_sdk/api/legal/models/legal_readiness_status_response.py
accelbyte_py_sdk/api/legal/models/localized_policy_version_object.py
accelbyte_py_sdk/api/legal/models/paged_retrieve_user_accepted_agreement_response.py
accelbyte_py_sdk/api/legal/models/paging.py
accelbyte_py_sdk/api/legal/models/permission.py
accelbyte_py_sdk/api/legal/models/policy_object.py
accelbyte_py_sdk/api/legal/models/policy_version_object.py
accelbyte_py_sdk/api/legal/models/policy_version_with_localized_version_object.py
accelbyte_py_sdk/api/legal/models/retrieve_accepted_agreement_response.py
accelbyte_py_sdk/api/legal/models/retrieve_base_policy_response.py
accelbyte_py_sdk/api/legal/models/retrieve_localized_policy_version_public_response.py
accelbyte_py_sdk/api/legal/models/retrieve_localized_policy_version_response.py
accelbyte_py_sdk_service_legal-0.26.0.dist-info/METADATA
accelbyte_py_sdk_service_legal-0.26.0.dist-info/WHEEL
accelbyte_py_sdk_service_legal-0.26.0.dist-info/top_level.txt
accelbyte_py_sdk_service_legal-0.26.0.dist-info/RECORD
