Metadata-Version: 2.4
Name: accelbyte-py-sdk-service-legal
Version: 0.26.0
Summary: AccelByte Python SDK - AccelByte Gaming Services Legal Service
Requires-Python: >=3.9
Requires-Dist: accelbyte-py-sdk-core
